hyponcloud2mqtt/__init__.py
hyponcloud2mqtt/_version.py
hyponcloud2mqtt/config.py
hyponcloud2mqtt/data_fetcher.py
hyponcloud2mqtt/data_merger.py
hyponcloud2mqtt/discovery.py
hyponcloud2mqtt/health_server.py
hyponcloud2mqtt/http_client.py
hyponcloud2mqtt/main.py
hyponcloud2mqtt/mqtt_client.py
hyponcloud2mqtt-1.0.0.dist-info/licenses/LICENSE
hyponcloud2mqtt-1.0.0.dist-info/METADATA
hyponcloud2mqtt-1.0.0.dist-info/WHEEL
hyponcloud2mqtt-1.0.0.dist-info/entry_points.txt
hyponcloud2mqtt-1.0.0.dist-info/top_level.txt
hyponcloud2mqtt-1.0.0.dist-info/RECORD
