Metadata-Version: 2.4
Name: hyponcloud2mqtt
Version: 1.0.0
Summary: A daemon to fetch data from HTTP and publish to MQTT
License-Expression: AGPL-3.0-or-later
Project-URL: Homepage, https://github.com/fligneul/hyponcloud2mqtt
Project-URL: Bug Tracker, https://github.com/fligneul/hyponcloud2mqtt/issues
Classifier: Programming Language :: Python :: 3
Classifier: Operating System :: OS Independent
Requires-Python: >=3.11
License-File: LICENSE
Requires-Dist: requests
Requires-Dist: paho-mqtt
Requires-Dist: pyyaml
Provides-Extra: dev
Requires-Dist: pytest; extra == "dev"
Requires-Dist: responses; extra == "dev"
Requires-Dist: flake8; extra == "dev"
Requires-Dist: mypy; extra == "dev"
Requires-Dist: types-requests; extra == "dev"
Requires-Dist: types-PyYAML; extra == "dev"
Dynamic: license-file
